[
    {
        "id": 1,
        "category": "Geography",
        "name": "Global Explorer",
        "description": "Travel the world without leaving your chair! Test your knowledge of countries, cities, and landmarks.",
        "number_of_questions": 3,
        "questions": [
            {
                "type": "multiple",
                "difficulty": "medium",
                "category": "Geography",
                "question": "What is the capital of Seychelles?",
                "correct_answer": "Victoria",
                "incorrect_answers": [
                    "Luanda",
                    "Djamena",
                    "Tripoli"
                ]
            },
            {
                "type": "multiple",
                "difficulty": "medium",
                "category": "Geography",
                "question": "Which European city has the highest mileage of canals in the world?",
                "correct_answer": "Birmingham",
                "incorrect_answers": [
                    "Venice",
                    "Amsterdam",
                    "Berlin"
                ]
            },
            {
                "type": "multiple",
                "difficulty": "easy",
                "category": "Geography",
                "question": "Which country was NOT part of the Soviet Union?",
                "correct_answer": "Romania",
                "incorrect_answers": [
                    "Turkmenistan",
                    "Belarus",
                    "Tajikistan"
                ]
            }
        ],
        "image": "https://c8.alamy.com/comp/K179PN/explorer-world-globe-character-cartoon-K179PN.jpg"
    },
    {
        "id": 2,
        "category": "Entertainment",
        "name": "Music Maestro",
        "description": "Dive into the rhythm of melodies and beats! A perfect challenge for music enthusiasts.",
        "number_of_questions": 8,
        "questions": [
            {
                "type": "multiple",
                "difficulty": "medium",
                "category": "Entertainment: Music",
                "question": "Which of these artists has NOT been a member of dancehall group Major Lazer?",
                "correct_answer": "Skrillex",
                "incorrect_answers": [
                    "Diplo",
                    "Jillionaire",
                    "Walshy Fire"
                ]
            },
            {
                "type": "boolean",
                "difficulty": "easy",
                "category": "Entertainment: Music",
                "question": "American rapper Dr. Dre actually has a Ph.D. doctorate.",
                "correct_answer": "False",
                "incorrect_answers": [
                    "True"
                ]
            },
            {
                "type": "boolean",
                "difficulty": "medium",
                "category": "Entertainment: Music",
                "question": "Ashley Frangipane performs under the stage name Halsey.",
                "correct_answer": "True",
                "incorrect_answers": [
                    "False"
                ]
            },
            {
                "type": "boolean",
                "difficulty": "medium",
                "category": "Entertainment: Music",
                "question": "The Division Bell is the final album of the progressive rock band Pink Floyd.",
                "correct_answer": "False",
                "incorrect_answers": [
                    "True"
                ]
            },
            {
                "type": "multiple",
                "difficulty": "easy",
                "category": "Entertainment: Music",
                "question": "Which country does the band Rammstein hail from?",
                "correct_answer": "Germany",
                "incorrect_answers": [
                    "Austria",
                    "Armenia",
                    "Belgium"
                ]
            },
            {
                "type": "boolean",
                "difficulty": "medium",
                "category": "Entertainment: Music",
                "question": "Dave Grohl recorded the Foo Fighters debut,Foo Fighters, by himself.",
                "correct_answer": "True",
                "incorrect_answers": [
                    "False"
                ]
            },
            {
                "type": "multiple",
                "difficulty": "medium",
                "category": "Entertainment: Music",
                "question": "What country did Shirley Bassey originate from?",
                "correct_answer": "Wales",
                "incorrect_answers": [
                    "America",
                    "England",
                    "Canada"
                ]
            },
            {
                "type": "multiple",
                "difficulty": "easy",
                "category": "Entertainment: Music",
                "question": "Which brass instrument has the lowest pitch in an orchestra?",
                "correct_answer": "Tuba",
                "incorrect_answers": [
                    "Trumpet",
                    "Saxophone",
                    "Trombone"
                ]
            }
        ],
        "image": "https://png.pngtree.com/png-vector/20240801/ourlarge/pngtree-cartoon-male-orchestra-director-png-image_13056643.png"
    },
    {
        "id": 3,
        "category": "Entertainment",
        "name": "Star Gossip",
        "description": "How well do you know the world of fame and glamour? Take this quiz to find out!",
        "number_of_questions": 1,
        "questions": [
            {
                "type": "multiple",
                "difficulty": "medium",
                "category": "Celebrities",
                "question": "What year was O.J. Simpson aquitted of his murder charges?",
                "correct_answer": "1995",
                "incorrect_answers": [
                    "1992",
                    "1996",
                    "1991"
                ]
            }
        ],
        "image": "https://media.istockphoto.com/id/693210524/vector/pop-art-style-comics-panel-gossip-girl-whispering-secret-in-ear-word-of-mouth-vector.jpg?s=612x612&w=0&k=20&c=4YeSgU2oo9qW6tObPktTy_bW0L8RZKRw4X7B3YPi5pk="
    },
    {
        "id": 4,
        "category": "History",
        "name": "Time Travelers",
        "description": "Travel back in time and revisit the moments that shaped our world.",
        "number_of_questions": 4,
        "questions": [
            {
                "type": "multiple",
                "difficulty": "hard",
                "category": "History",
                "question": "What was the aim of the Umbrella Revolution in Hong Kong in 2014?",
                "correct_answer": "Genuine universal suffrage",
                "incorrect_answers": [
                    "Gaining Independence",
                    "Go back under British Rule",
                    "Lower taxes"
                ]
            },
            {
                "type": "multiple",
                "difficulty": "hard",
                "category": "History",
                "question": "The coat of arms of the King of Spain contains the arms from the monarchs of Castille, Leon, Aragon and which other former Iberian kingdom?",
                "correct_answer": "Navarre",
                "incorrect_answers": [
                    "Galicia",
                    "Granada",
                    "Catalonia"
                ]
            },
            {
                "type": "multiple",
                "difficulty": "hard",
                "category": "History",
                "question": "How many sonatas did Ludwig van Beethoven write?",
                "correct_answer": "32",
                "incorrect_answers": [
                    "50",
                    "31",
                    "21"
                ]
            },
            {
                "type": "multiple",
                "difficulty": "easy",
                "category": "History",
                "question": "Which of the following was Brazil was a former colony under?",
                "correct_answer": "Portugal",
                "incorrect_answers": [
                    "Spain",
                    "The Netherlands",
                    "France"
                ]
            }
        ],
        "image": "https://media.istockphoto.com/id/1094602572/vector/time-machine.jpg?s=612x612&w=0&k=20&c=EUIPzDujKyD6D9-XcPBV9LOivIeoRbjjA9MEXy6dfaA="
    },
    {
        "id": 5,
        "category": "Entertainment",
        "name": "Pixel Perfect",
        "description": "Level up your trivia game! A perfect challenge for gaming legends.",
        "number_of_questions": 9,
        "questions": [
            {
                "type": "multiple",
                "difficulty": "easy",
                "category": "Entertainment: Video Games",
                "question": "If a 360 no-scope is one full rotation before shooting, how many rotations would a 1080 no-scope be?",
                "correct_answer": "3",
                "incorrect_answers": [
                    "4",
                    "2",
                    "5"
                ]
            },
            {
                "type": "multiple",
                "difficulty": "hard",
                "category": "Entertainment: Video Games",
                "question": "What is the name of the main character in the video game VA-11 HALL-A: Cyberpunk Bartender Action?",
                "correct_answer": "Jill",
                "incorrect_answers": [
                    "Dana",
                    "Alma",
                    "Anna"
                ]
            },
            {
                "type": "multiple",
                "difficulty": "easy",
                "category": "Entertainment: Video Games",
                "question": "What is Gabe Newells favorite class in Team Fortress 2?",
                "correct_answer": "Spy",
                "incorrect_answers": [
                    "Heavy",
                    "Medic",
                    "Pyro"
                ]
            },
            {
                "type": "multiple",
                "difficulty": "hard",
                "category": "Entertainment: Video Games",
                "question": "What Touhou Project characters first ever appearance was as a midboss in the eighth game, Imperishable Night?",
                "correct_answer": "Tewi Inaba",
                "incorrect_answers": [
                    "Mystia Lorelei",
                    "Kaguya Houraisan",
                    "Rumia"
                ]
            },
            {
                "type": "multiple",
                "difficulty": "hard",
                "category": "Entertainment: Video Games",
                "question": "In the SHMUP series, Gradius, what is the name of the antagonist faction you fight against?",
                "correct_answer": "Bacterion",
                "incorrect_answers": [
                    "Bydo",
                    "Belsar",
                    "ORN Empire"
                ]
            },
            {
                "type": "multiple",
                "difficulty": "medium",
                "category": "Entertainment: Video Games",
                "question": "What is the world first video game console?",
                "correct_answer": "Magnavox Odyssey",
                "incorrect_answers": [
                    "Coleco Telstar",
                    "Nintendo Color TV Game",
                    "Atari 2600"
                ]
            },
            {
                "type": "multiple",
                "difficulty": "medium",
                "category": "Entertainment: Video Games",
                "question": "Which of these characters was NOT planned to be playable for Super Smash Bros. 64?",
                "correct_answer": "Peach",
                "incorrect_answers": [
                    "Bowser",
                    "Mewtwo",
                    "King Dedede"
                ]
            },
            {
                "type": "multiple",
                "difficulty": "easy",
                "category": "Entertainment: Video Games",
                "question": "Which game did NOT get financed via Crowdfunding?",
                "correct_answer": "Enter the Gungeon",
                "incorrect_answers": [
                    "Town of Salem",
                    "Undertale",
                    "Tower Unite"
                ]
            },
            {
                "type": "multiple",
                "difficulty": "medium",
                "category": "Entertainment: Video Games",
                "question": "In Hitman: Blood Money, what is the name of the target in the mission Death of a Showman?",
                "correct_answer": "Joseph Clarence",
                "incorrect_answers": [
                    "The Swing King",
                    "Maynard John",
                    "Manuel Delgado"
                ]
            }
        ],
        "image": "https://img.freepik.com/premium-photo/eerily-realistic-3d-animation-boy-blocks-mosaicinspired-pixel-perfect-cartoon_899449-375841.jpg"
    },
    {
        "id": 6,
        "category": "Science",
        "name": "Tech Titans",
        "description": "Crack the code! Ideal for computer enthusiasts and future tech moguls.",
        "number_of_questions": 4,
        "questions": [
            {
                "type": "multiple",
                "difficulty": "easy",
                "category": "Science: Computers",
                "question": "In computing, what does MIDI stand for?",
                "correct_answer": "Musical Instrument Digital Interface",
                "incorrect_answers": [
                    "Musical Interface of Digital Instruments",
                    "Modular Interface of Digital Instruments",
                    "Musical Instrument Data Interface"
                ]
            },
            {
                "type": "multiple",
                "difficulty": "medium",
                "category": "Science: Computers",
                "question": "Which of these is the name for the failed key escrow device introduced by the National Security Agency in 1993?",
                "correct_answer": "Clipper Chip",
                "incorrect_answers": [
                    "Enigma Machine",
                    "Skipjack",
                    "Nautilus"
                ]
            },
            {
                "type": "multiple",
                "difficulty": "medium",
                "category": "Science: Computers",
                "question": "Which of the following is a personal computer made by the Japanese company Fujitsu?",
                "correct_answer": "FM-7",
                "incorrect_answers": [
                    "PC-9801",
                    "Xmillennium ",
                    "MSX"
                ]
            },
            {
                "type": "boolean",
                "difficulty": "medium",
                "category": "Science: Computers",
                "question": "Its not possible to format a write-protected DVD-R Hard Disk.",
                "correct_answer": "True",
                "incorrect_answers": [
                    "False"
                ]
            }
        ],
        "image": "https://media.licdn.com/dms/image/v2/C4E0BAQGViODTU3fn-w/company-logo_200_200/company-logo_200_200/0/1649162499397/team_tech_titans_logo?e=2147483647&v=beta&t=1NZhpNSasNsvkkVvvpVFh66C70AvcH98k9doVYrEI30"
    },
    {
        "id": 7,
        "category": "Sports",
        "name": "Sporting Legends",
        "description": "Gear up for a challenge! Perfect for sports fans and trivia athletes.",
        "number_of_questions": 2,
        "questions": [
            {
                "type": "multiple",
                "difficulty": "easy",
                "category": "Sports",
                "question": "Which of the following sports is not part of the triathlon?",
                "correct_answer": "Horse-Riding",
                "incorrect_answers": [
                    "Cycling",
                    "Swimming",
                    "Running"
                ]
            },
            {
                "type": "boolean",
                "difficulty": "medium",
                "category": "Sports",
                "question": "Wilt Chamberlain scored his infamous 100-point-game against the New York Knicks in 1962.",
                "correct_answer": "True",
                "incorrect_answers": [
                    "False"
                ]
            }
        ],
        "image": "https://img.freepik.com/premium-vector/happy-children-playing-sports-outdoors-cartoon-style_657438-34747.jpg"
    },
    {
        "id": 8,
        "category": "Entertainment",
        "name": "Cinema Buff",
        "description": "Grab some popcorn and test your film trivia knowledge!",
        "number_of_questions": 3,
        "questions": [
            {
                "type": "multiple",
                "difficulty": "hard",
                "category": "Entertainment: Film",
                "question": "In what Disney movie can you spot the character Pac-Man in if you look closely enough in some scenes?",
                "correct_answer": "Tron",
                "incorrect_answers": [
                    "Big Hero 6",
                    "Fantasia",
                    "Monsters, Inc."
                ]
            },
            {
                "type": "boolean",
                "difficulty": "easy",
                "category": "Entertainment: Film",
                "question": "Actor Tommy Chong served prison time.",
                "correct_answer": "True",
                "incorrect_answers": [
                    "False"
                ]
            },
            {
                "type": "multiple",
                "difficulty": "easy",
                "category": "Entertainment: Film",
                "question": "Who directed the 2015 movie The Revenant?",
                "correct_answer": "Alejandro G. Irritu",
                "incorrect_answers": [
                    "Christopher Nolan",
                    "David Fincher",
                    "Wes Anderson"
                ]
            }
        ],
        "image": "https://thumbs.dreamstime.com/b/cartoon-cinema-building-vector-modern-exterior-facade-urban-architecture-flat-design-style-illustration-88982586.jpg"
    },
    {
        "id": 9,
        "category": "Entertainment",
        "name": "Comic Crusader",
        "description": "Unleash your inner hero and conquer this comic-themed trivia!",
        "number_of_questions": 1,
        "questions": [
            {
                "type": "multiple",
                "difficulty": "easy",
                "category": "Entertainment: Comics",
                "question": "Which one of these superhero teams appears in the Invincible comics?",
                "correct_answer": "Guardians of the Globe",
                "incorrect_answers": [
                    "Avengers",
                    "Justice League",
                    "Teenage Mutant Ninja Turtles"
                ]
            }
        ],
        "image": "https://marketplace.canva.com/EAF7iUA9Uhs/1/0/1600w/canva-colorful-festive-retro-superhero-comic-strip-bqnFhYQ96iY.jpg"
    },
    {
        "id": 10,
        "category": "Science",
        "name": "Nature Nerd",
        "description": "Explore the wonders of science and the beauty of nature.",
        "number_of_questions": 3,
        "questions": [
            {
                "type": "multiple",
                "difficulty": "medium",
                "category": "Science and Nature",
                "question": "Which one of these scientists conducted the Gold Foil Experiment which concluded that atoms are mostly made of empty space?",
                "correct_answer": "Ernest Rutherford",
                "incorrect_answers": [
                    "Joseph John Thomson",
                    "Archimedes",
                    "Niels Henrik David Bohr"
                ]
            },
            {
                "type": "multiple",
                "difficulty": "medium",
                "category": "Science and Nature",
                "question": "What polymer is used to make CDs, safety goggles and riot shields?",
                "correct_answer": "Polycarbonate",
                "incorrect_answers": [
                    "Rubber",
                    "Nylon",
                    "Bakelite"
                ]
            },
            {
                "type": "multiple",
                "difficulty": "medium",
                "category": "Science Nature",
                "question": "Gannymede is the largest moon of which planet?",
                "correct_answer": "Jupiter",
                "incorrect_answers": [
                    "Uranus",
                    "Neptune",
                    "Mars"
                ]
            }
        ],
        "image": "https://mlpnk72yciwc.i.optimole.com/cqhiHLc.IIZS~2ef73/w:350/h:350/q:75/rt:fill/g:ce/https://bleedingcool.com/wp-content/uploads/2023/02/diary-of-a-nature-nerd-350x350.jpg"
    },
    {
        "id": 11,
        "category": "Vehicles",
        "name": "Auto Aficionado",
        "description": "Rev your engines and test your knowledge of all things vehicular.",
        "number_of_questions": 5,
        "questions": [
            {
                "type": "multiple",
                "difficulty": "medium",
                "category": "Vehicles",
                "question": "Which Japanese company is the world's largest manufacturer of motorcycles?",
                "correct_answer": "Honda",
                "incorrect_answers": [
                    "Yamaha",
                    "Suzuki",
                    "Kawasaki"
                ]
            }
        ],
        "image": "https://img.freepik.com/premium-photo/cartoon-digital-avatars-auto-aficionado-holding-clipboard-checking-off-items-car_216520-94300.jpg?w=360"
    },
    {
        "id": 12,
        "category": "Entertainment",
        "name": "Animated Antics",
        "description": "From classic cartoons to modern animations, see how much you know!",
        "number_of_questions": 1,
        "questions": [
            {
                "type": "boolean",
                "difficulty": "medium",
                "category": "Entertainment: Cartoon and Animations",
                "question": "Nutcracker Suite was one of the musical pieces featured in Disney 1940's film Fantasia.",
                "correct_answer": "True",
                "incorrect_answers": [
                    "False"
                ]
            }
        ],
        "image": "https://cartoonresearch.com/wp-content/uploads/2024/06/Wizard-Arts-344.jpg"
    },
    {
        "id": 13,
        "category": "Entertainment",
        "name": "TV Buff",
        "description": "Binge-watched every series? Prove it with this television trivia.",
        "number_of_questions": 7,
        "questions": [
            {
                "type": "multiple",
                "difficulty": "easy",
                "category": "Entertainment: Television",
                "question": "When did the TV show Rick and Morty first air on Adult Swim?",
                "correct_answer": "2013",
                "incorrect_answers": [
                    "2014",
                    "2016",
                    "2015"
                ]
            },
            {
                "type": "multiple",
                "difficulty": "medium",
                "category": "Entertainment: Television",
                "question": "In *Grey's Anatomy*, which hospital do the characters primarily work at?",
                "correct_answer": "Seattle Grace Hospital",
                "incorrect_answers": [
                    "Presbyterian Hospital",
                    "Mercy West Hospital",
                    "St. Mary's Hospital"
                ]
            },
            {
                "type": "boolean",
                "difficulty": "easy",
                "category": "Entertainment: Television",
                "question": "Raymond 'Red' Reddington is a former Navy officer in *The Blacklist*.",
                "correct_answer": "True",
                "incorrect_answers": [
                    "False"
                ]
            },
            {
                "type": "multiple",
                "difficulty": "medium",
                "category": "Entertainment: Television",
                "question": "What supernatural ability does Elena Gilbert NOT have in *The Vampire Diaries*?",
                "correct_answer": "Shapeshifting",
                "incorrect_answers": [
                    "Heightened senses",
                    "Immortality",
                    "Compulsion"
                ]
            },
            {
                "type": "multiple",
                "difficulty": "hard",
                "category": "Entertainment: Television",
                "question": "What is the name of the powerful family central to *The Originals*?",
                "correct_answer": "The Mikaelsons",
                "incorrect_answers": [
                    "The Salvatore Brothers",
                    "The Petrovas",
                    "The Lockwoods"
                ]
            },
            {
                "type": "boolean",
                "difficulty": "easy",
                "category": "Entertainment: Television",
                "question": "In *Grey's Anatomy*, Derek Shepherd is also known as 'McDreamy'.",
                "correct_answer": "True",
                "incorrect_answers": [
                    "False"
                ]
            },
            {
                "type": "multiple",
                "difficulty": "medium",
                "category": "Entertainment: Television",
                "question": "What is the secret behind Raymond Reddington's knowledge of the criminal underworld in *The Blacklist*?",
                "correct_answer": "He's a former criminal mastermind.",
                "incorrect_answers": [
                    "He's an undercover FBI agent.",
                    "He's a journalist investigating crime.",
                    "He's a retired detective."
                ]
            }
        ],
        "image": "https://encrypted-tbn0.gstatic.com/images?q=tbn:ANd9GcSDL9_ENGeUDV5QbUAYxxlt_PIG3js3KoZa4Q&s"
    },
    {
        "id": 14,
        "category": "Entertainment",
        "name": "Otaku Oracle",
        "description": "Dive into the world of anime and manga with this specialized quiz.",
        "number_of_questions": 4,
        "questions": [
            {
                "type": "multiple",
                "difficulty": "easy",
                "category": "Entertainment: Japanese Anime and Manga",
                "question": "In Fairy Tail, what is the nickname of Natsu Dragneel?",
                "correct_answer": "The Salamander",
                "incorrect_answers": [
                    "The Dragon Slayer",
                    "The Dragon",
                    "The Demon"
                ]
            }
        ],
        "image": "https://encrypted-tbn0.gstatic.com/images?q=tbn:ANd9GcSzEgPz4O7rFNKZfnPiaYr9_AC0_BkR9f8rcw&s"
    },
    {
        "id": 15,
        "category": "Science",
        "name": "Myth Master",
        "description": "From Greek gods to Norse legends, test your mythological knowledge.",
        "number_of_questions": 3,
        "questions": [
            {
                "type": "boolean",
                "difficulty": "medium",
                "category": "Mythology",
                "question": "According to Norse mythology, Loki is a mother.",
                "correct_answer": "True",
                "incorrect_answers": [
                    "False"
                ]
            }
        ],
        "image": "https://encrypted-tbn0.gstatic.com/images?q=tbn:ANd9GcTTjiuhdUEuLntoaivqfwU8rK-Ci7o88pmVDQ&s"
    },
    {
        "id": 16,
        "category": "Art",
        "name": "Art Aficionado",
        "description": "Brush up on your art history and masterpieces in this quiz.",
        "number_of_questions": 1,
        "questions": [
            {
                "type": "multiple",
                "difficulty": "easy",
                "category": "Art",
                "question": "Who painted the Sistine Chapel?",
                "correct_answer": "Michelangelo",
                "incorrect_answers": [
                    "Leonardo da Vinci",
                    "Pablo Picasso",
                    "Raphael"
                ]
            }
        ],
        "image": "https://img.freepik.com/premium-photo/man-artist-2d-cartoon-illustraton-white-background-high_889056-26894.jpg"
    },
    {
        "id": 17,
        "category": "General Knowledge",
        "name": "Trivia Titan",
        "description": "A mix of questions from various topics to challenge your intellect.",
        "number_of_questions": 4,
        "questions": [
            {
                "type": "boolean",
                "difficulty": "easy",
                "category": "General Knowledge",
                "question": "Dihydrogen Monoxide was banned due to health risks after being discovered in 1983 inside swimming pools and drinking water.",
                "correct_answer": "False",
                "incorrect_answers": [
                    "True"
                ]
            },
            {
                "type": "multiple",
                "difficulty": "medium",
                "category": "General Knowledge",
                "question": "Which of these is the name of a Japanese system of alternative medicine, literally meaning finger pressure?",
                "correct_answer": "Shiatsu",
                "incorrect_answers": [
                    "Ukiyo",
                    "Majime",
                    "Ikigai"
                ]
            },
            {
                "type": "multiple",
                "difficulty": "hard",
                "category": "General Knowledge",
                "question": "If someone said you are olid, what would they mean?",
                "correct_answer": "You smell extremely unpleasant.",
                "incorrect_answers": [
                    "You are out of shape/weak.",
                    "Your appearance is repulsive.",
                    "You are incomprehensible/an idiot."
                ]
            },
            {
                "type": "multiple",
                "difficulty": "easy",
                "category": "General Knowledge",
                "question": "What does a funambulist walk on?",
                "correct_answer": "A Tight Rope",
                "incorrect_answers": [
                    "Broken Glass",
                    "Balls",
                    "The Moon"
                ]
            }
        ],
        "image": "https://thumbs.dreamstime.com/b/characters-answer-test-question-intellect-show-gaming-cartoon-man-woman-pressing-button-answering-quiz-questions-game-118076003.jpg"
    },
    {
        "id": 18,
        "category": "Entertainment",
        "name": "Bookworm Bonanza",
        "description": "Test your knowledge of literature, from classics to modern bestsellers.",
        "number_of_questions": 1,
        "questions": [
            {
                "type": "multiple",
                "difficulty": "medium",
                "category": "Entertainment: Books",
                "question": "In the Harry Potter novels, what must a Hogwarts student do to enter the Ravenclaw Common Room?",
                "correct_answer": "Answer a riddle",
                "incorrect_answers": [
                    "Rhythmically tap barrels with a wand",
                    "Speak a password",
                    "Knock in sequence"
                ]
            }
        ],
        "image": "https://thumbs.dreamstime.com/b/set-cartoon-people-reading-books-different-age-vector-illustration-52609442.jpg"
    },
    {
        "id": 19,
        "category": "Science",
        "name": "Gadget Guru",
        "description": "Explore the latest and greatest in the world of science and gadgets.",
        "number_of_questions": 1,
        "questions": [
            {
                "type": "multiple",
                "difficulty": "easy",
                "category": "Science: Gadgets",
                "question": "When did the CD begin to appear on the consumer market?",
                "correct_answer": "1982",
                "incorrect_answers": [
                    "1992",
                    "1972",
                    "1962"
                ]
            }
        ],
        "image": "https://i.pinimg.com/736x/55/27/5b/55275b315345a2523f329ab5e358d105.jpg"
    }
]